[
  {
    "category": "kuchyne",
    "images": [
      "/sources/referencie/kuchyne/1.jpg",
      "/sources/referencie/kuchyne/2.jpg",
      "/sources/referencie/kuchyne/3.jpg",
      "/sources/referencie/kuchyne/4.jpg",
      "/sources/referencie/kuchyne/5.jpg",
      "/sources/referencie/kuchyne/6.jpg",
      "/sources/referencie/kuchyne/7.jpg",
      "/sources/referencie/kuchyne/8.jpg",
      "/sources/referencie/kuchyne/9.jpg",
      "/sources/referencie/kuchyne/10.jpg",
      "/sources/referencie/kuchyne/11.jpg",
      "/sources/referencie/kuchyne/12.jpg",
      "/sources/referencie/kuchyne/13.jpg",
      "/sources/referencie/kuchyne/14.jpg",
      "/sources/referencie/kuchyne/15.jpg",
      "/sources/referencie/kuchyne/16.jpg",
      "/sources/referencie/kuchyne/17.jpg",
      "/sources/referencie/kuchyne/18.jpg",
      "/sources/referencie/kuchyne/19.jpg",
      "/sources/referencie/kuchyne/20.jpg",
      "/sources/referencie/kuchyne/21.jpg",
      "/sources/referencie/kuchyne/22.jpg",
      "/sources/referencie/kuchyne/23.jpg",
      "/sources/referencie/kuchyne/24.jpg",
      "/sources/referencie/kuchyne/25.jpg",
      "/sources/referencie/kuchyne/26.jpg",
      "/sources/referencie/kuchyne/27.jpg",
      "/sources/referencie/kuchyne/28.jpg",
      "/sources/referencie/kuchyne/29.jpg",
      "/sources/referencie/kuchyne/30.jpg",
      "/sources/referencie/kuchyne/31.jpg",
      "/sources/referencie/kuchyne/32.jpg",
      "/sources/referencie/kuchyne/33.jpg",
      "/sources/referencie/kuchyne/34.jpg",
      "/sources/referencie/kuchyne/35.jpg",
      "/sources/referencie/kuchyne/36.jpg",
      "/sources/referencie/kuchyne/37.jpg",
      "/sources/referencie/kuchyne/38.jpg",
      "/sources/referencie/kuchyne/39.jpg",
      "/sources/referencie/kuchyne/40.jpg",
      "/sources/referencie/kuchyne/41.jpg",
      "/sources/referencie/kuchyne/42.jpg",
      "/sources/referencie/kuchyne/43.jpg",
      "/sources/referencie/kuchyne/44.jpg",
      "/sources/referencie/kuchyne/45.jpg",
      "/sources/referencie/kuchyne/46.jpg",
      "/sources/referencie/kuchyne/47.jpg",
      "/sources/referencie/kuchyne/48.jpg",
      "/sources/referencie/kuchyne/49.jpg",
      "/sources/referencie/kuchyne/50.jpg",
      "/sources/referencie/kuchyne/51.jpg",
      "/sources/referencie/kuchyne/52.jpg",
      "/sources/referencie/kuchyne/53.jpg",
      "/sources/referencie/kuchyne/54.jpg",
      "/sources/referencie/kuchyne/55.jpg",
      "/sources/referencie/kuchyne/56.jpg",
      "/sources/referencie/kuchyne/57.jpg",
      "/sources/referencie/kuchyne/58.jpg",
      "/sources/referencie/kuchyne/59.jpg",
      "/sources/referencie/kuchyne/60.jpg",
      "/sources/referencie/kuchyne/61.jpg",
      "/sources/referencie/kuchyne/62.jpg",
      "/sources/referencie/kuchyne/63.jpg",
      "/sources/referencie/kuchyne/64.jpg",
      "/sources/referencie/kuchyne/65.jpg",
      "/sources/referencie/kuchyne/66.jpg",
      "/sources/referencie/kuchyne/67.jpg",
      "/sources/referencie/kuchyne/68.jpg",
      "/sources/referencie/kuchyne/69.jpg",
      "/sources/referencie/kuchyne/70.jpg",
      "/sources/referencie/kuchyne/71.jpg",
      "/sources/referencie/kuchyne/73.jpg",
      "/sources/referencie/kuchyne/74.jpg",
      "/sources/referencie/kuchyne/FB_IMG_1648668470561.jpg",
      "/sources/referencie/kuchyne/FB_IMG_1648668637517.jpg",
      "/sources/referencie/kuchyne/FB_IMG_1648668651032.jpg",
      "/sources/referencie/kuchyne/FB_IMG_1648668702392.jpg",
      "/sources/referencie/kuchyne/FB_IMG_1648668707787.jpg",
      "/sources/referencie/kuchyne/kuchyna-cierna.jpg",
      "/sources/referencie/kuchyne/kuchyna-do-U.jpg",
      "/sources/referencie/kuchyne/kuchyna-duplin.jpg"
    ]
  },
  {
    "category": "kupelne",
    "images": [
      "/sources/referencie/kupelne/1.jpg",
      "/sources/referencie/kupelne/2.jpg",
      "/sources/referencie/kupelne/3.jpg",
      "/sources/referencie/kupelne/4.jpg",
      "/sources/referencie/kupelne/5.jpg",
      "/sources/referencie/kupelne/6.jpg",
      "/sources/referencie/kupelne/7.jpg",
      "/sources/referencie/kupelne/8.jpg",
      "/sources/referencie/kupelne/9.jpg",
      "/sources/referencie/kupelne/10.jpg",
      "/sources/referencie/kupelne/11.jpg",
      "/sources/referencie/kupelne/12.jpg",
      "/sources/referencie/kupelne/13.jpg",
      "/sources/referencie/kupelne/14.jpg",
      "/sources/referencie/kupelne/15.jpg",
      "/sources/referencie/kupelne/16.jpg",
      "/sources/referencie/kupelne/17.jpg",
      "/sources/referencie/kupelne/18.jpg",
      "/sources/referencie/kupelne/19.jpg",
      "/sources/referencie/kupelne/20.jpg",
      "/sources/referencie/kupelne/21.jpg",
      "/sources/referencie/kupelne/22.jpg"
    ]
  },
  {
    "category": "vstavane-skrine",
    "images": [
      "/sources/referencie/vstavane skrine/1.jpg",
      "/sources/referencie/vstavane skrine/2.jpg",
      "/sources/referencie/vstavane skrine/3.jpg",
      "/sources/referencie/vstavane skrine/4.jpg",
      "/sources/referencie/vstavane skrine/5.jpg",
      "/sources/referencie/vstavane skrine/6.jpg",
      "/sources/referencie/vstavane skrine/7.jpg",
      "/sources/referencie/vstavane skrine/8.jpg",
      "/sources/referencie/vstavane skrine/9.jpg",
      "/sources/referencie/vstavane skrine/10.jpg",
      "/sources/referencie/vstavane skrine/11.jpg",
      "/sources/referencie/vstavane skrine/12.jpg",
      "/sources/referencie/vstavane skrine/13.jpg",
      "/sources/referencie/vstavane skrine/14.jpg",
      "/sources/referencie/vstavane skrine/15.jpg",
      "/sources/referencie/vstavane skrine/17.jpg",
      "/sources/referencie/vstavane skrine/18.jpg",
      "/sources/referencie/vstavane skrine/19.jpg",
      "/sources/referencie/vstavane skrine/20.jpg",
      "/sources/referencie/vstavane skrine/21.jpg",
      "/sources/referencie/vstavane skrine/22.jpg",
      "/sources/referencie/vstavane skrine/23.jpg",
      "/sources/referencie/vstavane skrine/24.jpg",
      "/sources/referencie/vstavane skrine/25.jpg",
      "/sources/referencie/vstavane skrine/26.jpg",
      "/sources/referencie/vstavane skrine/27.jpg",
      "/sources/referencie/vstavane skrine/28.jpg",
      "/sources/referencie/vstavane skrine/29.jpg",
      "/sources/referencie/vstavane skrine/30.jpg",
      "/sources/referencie/vstavane skrine/31.jpg",
      "/sources/referencie/vstavane skrine/32.jpg",
      "/sources/referencie/vstavane skrine/33.jpg",
      "/sources/referencie/vstavane skrine/34.jpg",
      "/sources/referencie/vstavane skrine/35.jpg",
      "/sources/referencie/vstavane skrine/36.jpg",
      "/sources/referencie/vstavane skrine/37.jpg",
      "/sources/referencie/vstavane skrine/38.jpg",
      "/sources/referencie/vstavane skrine/39.jpg",
      "/sources/referencie/vstavane skrine/40.jpg",
      "/sources/referencie/vstavane skrine/41.jpg"
    ]
  },
  {
    "category": "obyvacie-izby",
    "images": [
      "/sources/referencie/obyvacie izby/1.jpg",
      "/sources/referencie/obyvacie izby/2.jpg",
      "/sources/referencie/obyvacie izby/3.jpg",
      "/sources/referencie/obyvacie izby/5.jpg",
      "/sources/referencie/obyvacie izby/FB_IMG_1648668766103.jpg",
      "/sources/referencie/obyvacie izby/IMG-20210712-WA0037.jpg",
      "/sources/referencie/obyvacie izby/obyvackova-stena-2.jpg",
      "/sources/referencie/obyvacie izby/obyvackova-stena-3.jpg",
      "/sources/referencie/obyvacie izby/obyvackova-stena.jpg"
    ]
  },
  {
    "category": "postele",
    "images": [
      "/sources/referencie/postele a nocne stoliky/1.jpg",
      "/sources/referencie/postele a nocne stoliky/2.jpg",
      "/sources/referencie/postele a nocne stoliky/3.jpg",
      "/sources/referencie/postele a nocne stoliky/4.jpg",
      "/sources/referencie/postele a nocne stoliky/5.jpg",
      "/sources/referencie/postele a nocne stoliky/6.jpg",
      "/sources/referencie/postele a nocne stoliky/7.jpg",
      "/sources/referencie/postele a nocne stoliky/8.jpg",
      "/sources/referencie/postele a nocne stoliky/9.jpg",
      "/sources/referencie/postele a nocne stoliky/10.jpg",
      "/sources/referencie/postele a nocne stoliky/FB_IMG_1648668849167.jpg",
      "/sources/referencie/postele a nocne stoliky/detska-postel-Miska-1.jpg",
      "/sources/referencie/postele a nocne stoliky/nocny-stolik-bieli-1.jpg",
      "/sources/referencie/postele a nocne stoliky/nocny-stolik-bieli-2.jpg",
      "/sources/referencie/postele a nocne stoliky/nocny-stolik-bieli.jpg",
      "/sources/referencie/postele a nocne stoliky/nocny-stolik-k-posteli.jpg",
      "/sources/referencie/postele a nocne stoliky/postel-s-podsvietenim-1.jpg",
      "/sources/referencie/postele a nocne stoliky/postel-s-podsvietenim.jpg"
    ]
  },
  {
    "category": "schodiska",
    "images": [
      "/sources/referencie/schodiska/schodisko-1.jpg",
      "/sources/referencie/schodiska/schodisko-2.jpg",
      "/sources/referencie/schodiska/schodisko-3.jpg",
      "/sources/referencie/schodiska/schodisko-4.jpg",
      "/sources/referencie/schodiska/schodisko-5.jpg",
      "/sources/referencie/schodiska/schodisko.jpg",
      "/sources/referencie/schodiska/278087174_5705072039509251_620473692532580821_n.jpg",
      "/sources/referencie/schodiska/278113042_5705071649509290_4495710743442976595_n.jpg"
    ]
  },
  {
    "category": "stoly",
    "images": [
      "/sources/referencie/stoly/20220825_171114-scaled.jpg",
      "/sources/referencie/stoly/20220826_082609-scaled.jpg",
      "/sources/referencie/stoly/IMG-20210712-WA0034.jpg",
      "/sources/referencie/stoly/pracovny-stol-1.jpg",
      "/sources/referencie/stoly/pracovny-stol-2.jpg",
      "/sources/referencie/stoly/pracovny-stolik-1.jpg",
      "/sources/referencie/stoly/pracovny-stolik.jpg",
      "/sources/referencie/stoly/stol-dreveny.jpg",
      "/sources/referencie/stoly/stolik-do-obyvacky-1.jpg",
      "/sources/referencie/stoly/stolik-do-obyvacky.jpg"
    ]
  },
  {
    "category": "vesiakove",
    "images": [
      "/sources/referencie/vesiakove steny, botniky a komody/1.jpg",
      "/sources/referencie/vesiakove steny, botniky a komody/2.jpg",
      "/sources/referencie/vesiakove steny, botniky a komody/3.jpg",
      "/sources/referencie/vesiakove steny, botniky a komody/5.jpg",
      "/sources/referencie/vesiakove steny, botniky a komody/6.jpg",
      "/sources/referencie/vesiakove steny, botniky a komody/7.jpg",
      "/sources/referencie/vesiakove steny, botniky a komody/8.jpg",
      "/sources/referencie/vesiakove steny, botniky a komody/9.jpg",
      "/sources/referencie/vesiakove steny, botniky a komody/10.jpg",
      "/sources/referencie/vesiakove steny, botniky a komody/11.jpg",
      "/sources/referencie/vesiakove steny, botniky a komody/12.jpg",
      "/sources/referencie/vesiakove steny, botniky a komody/13.jpg",
      "/sources/referencie/vesiakove steny, botniky a komody/14.jpg"
    ]
  },
  {
    "category": "exterierove",
    "images": [
      "/sources/referencie/exterierove produkty/altanok.jpg",
      "/sources/referencie/exterierove produkty/balkon-ganok.jpg",
      "/sources/referencie/exterierove produkty/botnik-do-chodbi.jpg",
      "/sources/referencie/exterierove produkty/kriz-1-1.jpg",
      "/sources/referencie/exterierove produkty/kriz-2-1.jpg",
      "/sources/referencie/exterierove produkty/oblozenie-steny-s-drevom-1.jpg",
      "/sources/referencie/exterierove produkty/oblozenie-steny-s-drevom-2.jpg",
      "/sources/referencie/exterierove produkty/plotik-1.jpg",
      "/sources/referencie/exterierove produkty/plotik-2.jpg",
      "/sources/referencie/exterierove produkty/plotik-3.jpg",
      "/sources/referencie/exterierove produkty/plotik-4.jpg",
      "/sources/referencie/exterierove produkty/plotik.jpg",
      "/sources/referencie/exterierove produkty/pristresok-nad-dvere.jpg",
      "/sources/referencie/exterierove produkty/pristresok.jpg",
      "/sources/referencie/exterierove produkty/terasa.jpg",
      "/sources/referencie/exterierove produkty/zahradny-domcek-1.jpg",
      "/sources/referencie/exterierove produkty/zahradny-domcek-na-naradie-vnutro-2.jpg",
      "/sources/referencie/exterierove produkty/zahradny-domcek-na-naradie-vnutro.jpg",
      "/sources/referencie/exterierove produkty/zahradny-domcek-na-naradie.jpg"
    ]
  },
  {
    "category": "ine",
    "images": [
      "/sources/referencie/Ine/archiv-1.jpg",
      "/sources/referencie/Ine/denko-1.jpg",
      "/sources/referencie/Ine/drevena-oblozka-nad-postel.jpg",
      "/sources/referencie/Ine/dvierka-do-sachty-v-bytovke-1.jpg",
      "/sources/referencie/Ine/dvierka-do-sachty-v-bytovke.jpg",
      "/sources/referencie/Ine/dvierka-k-poistkam-v-bytovke-2.jpg",
      "/sources/referencie/Ine/dvierka-k-poistkam-v-bytovke.jpg",
      "/sources/referencie/Ine/garniz-2.jpg",
      "/sources/referencie/Ine/garniz.jpg",
      "/sources/referencie/Ine/hokerlik-1.jpg",
      "/sources/referencie/Ine/hokerlik.jpg",
      "/sources/referencie/Ine/kvetinac-na-stromcek-1.jpg",
      "/sources/referencie/Ine/kvetinac-na-stromcek-2.jpg",
      "/sources/referencie/Ine/sachy-2.jpg",
      "/sources/referencie/Ine/sachy.jpg",
      "/sources/referencie/Ine/stojan-na-vino-2.jpg",
      "/sources/referencie/Ine/stojan-na-vino-3.jpg",
      "/sources/referencie/Ine/stojan-na-vino.jpg"
    ]
  }
]